virt_lightning/__init__.py
virt_lightning/api.py
virt_lightning/configuration.py
virt_lightning/shell.py
virt_lightning/symbols.py
virt_lightning/templates.py
virt_lightning/ui.py
virt_lightning/util.py
virt_lightning/virt_lightning.py
virt_lightning-2.5.0.dist-info/licenses/LICENSE-2.0.txt
virt_lightning-2.5.0.dist-info/METADATA
virt_lightning-2.5.0.dist-info/WHEEL
virt_lightning-2.5.0.dist-info/entry_points.txt
virt_lightning-2.5.0.dist-info/top_level.txt
virt_lightning-2.5.0.dist-info/RECORD
