Metadata-Version: 2.4
Name: virt-lightning
Version: 2.5.0
Summary: Deploy your testing VM in a couple of seconds
Author-email: Gonéri Le Bouder <goneri@lebouder.net>
License-Expression: Apache-2.0
Project-URL: Homepage, https://virt-lightning.org/
Project-URL: Source, https://github.com/virt-lightning/virt-lightning
Keywords: libvirt,cloud,qemu,cloudinit
Classifier: Environment :: Console
Classifier: Programming Language :: Python :: 3
Classifier: Operating System :: POSIX :: Linux
Requires-Python: >=3.9
License-File: LICENSE-2.0.txt
Requires-Dist: libvirt-python>=11.10.0
Requires-Dist: pyyaml>=6.0.3
Provides-Extra: urwid
Requires-Dist: urwid>=2.6.16; extra == "urwid"
Dynamic: license-file
